{
  "legislative_session": "2026",
  "identifier": "HB 1694",
  "title": "Establishes the \"Act Against Abusive Website Access Litigation\"",
  "from_organization": "~{\"classification\": \"lower\"}",
  "classification": [
    "bill"
  ],
  "subject": [
    "ATTORNEY GENERAL",
    "CIVIL PROCEDURE",
    "COURTS",
    "DISABILITIES",
    "INTERNET AND E-MAIL"
  ],
  "abstracts": [],
  "other_titles": [
    {
      "note": "official",
      "title": "HCS HBs 1694, 1674, 1780, 2056, 2312 & 1755"
    }
  ],
  "other_identifiers": [
    {
      "identifier": "ocd-bill-mo-2026-hb1694"
    }
  ],
  "actions": [
    {
      "description": "Prefiled (H)",
      "date": "2025-12-01T06:00:00+00:00",
      "organization_id": "~{\"classification\": \"lower\"}",
      "classification": [],
      "related_entities": [],
      "_processing": {
        "log_file_created": "2026-07-13T06:05:21Z"
      }
    },
    {
      "description": "Read First Time (H)",
      "date": "2026-01-07T06:00:00+00:00",
      "organization_id": "~{\"classification\": \"lower\"}",
      "classification": [],
      "related_entities": [],
      "_processing": {
        "log_file_created": "2026-07-13T06:05:21Z"
      }
    },
    {
      "description": "Read Second Time (H)",
      "date": "2026-01-08T06:00:00+00:00",
      "organization_id": "~{\"classification\": \"lower\"}",
      "classification": [
        "reading-2"
      ],
      "related_entities": [],
      "_processing": {
        "log_file_created": "2026-07-13T06:05:21Z"
      }
    },
    {
      "description": "Referred: General Laws(H)",
      "date": "2026-01-08T06:00:00+00:00",
      "organization_id": "~{\"classification\": \"lower\"}",
      "classification": [
        "referral-committee"
      ],
      "related_entities": [],
      "_processing": {
        "log_file_created": "2026-07-13T06:05:21Z"
      }
    },
    {
      "description": "Public Hearing Completed (H)",
      "date": "2026-01-14T06:00:00+00:00",
      "organization_id": "~{\"classification\": \"lower\"}",
      "classification": [],
      "related_entities": [],
      "_processing": {
        "log_file_created": "2026-07-13T06:05:21Z"
      }
    },
    {
      "description": "Executive Session Completed (H)",
      "date": "2026-01-21T06:00:00+00:00",
      "organization_id": "~{\"classification\": \"lower\"}",
      "classification": [],
      "related_entities": [],
      "_processing": {
        "log_file_created": "2026-07-13T06:05:21Z"
      }
    },
    {
      "description": "HCS Voted Do Pass (H)",
      "date": "2026-01-21T06:00:00+00:00",
      "organization_id": "~{\"classification\": \"lower\"}",
      "classification": [
        "committee-passage"
      ],
      "related_entities": [],
      "_processing": {
        "log_file_created": "2026-07-13T06:05:21Z"
      }
    },
    {
      "description": "HCS Reported Do Pass (H) - AYES: 14 NOES: 0 PRESENT: 0",
      "date": "2026-01-22T06:00:00+00:00",
      "organization_id": "~{\"classification\": \"lower\"}",
      "classification": [
        "committee-passage"
      ],
      "related_entities": [],
      "_processing": {
        "log_file_created": "2026-07-13T06:05:21Z"
      }
    },
    {
      "description": "Referred: Rules - Legislative(H)",
      "date": "2026-01-27T06:00:00+00:00",
      "organization_id": "~{\"classification\": \"lower\"}",
      "classification": [
        "referral-committee"
      ],
      "related_entities": [],
      "_processing": {
        "log_file_created": "2026-07-13T06:05:21Z"
      }
    },
    {
      "description": "Executive Session Completed (H)",
      "date": "2026-01-29T06:00:00+00:00",
      "organization_id": "~{\"classification\": \"lower\"}",
      "classification": [],
      "related_entities": [],
      "_processing": {
        "log_file_created": "2026-07-13T06:05:21Z"
      }
    },
    {
      "description": "Voted Do Pass (H)",
      "date": "2026-01-29T06:00:00+00:00",
      "organization_id": "~{\"classification\": \"lower\"}",
      "classification": [
        "committee-passage"
      ],
      "related_entities": [],
      "_processing": {
        "log_file_created": "2026-07-13T06:05:21Z"
      }
    },
    {
      "description": "Reported Do Pass (H) - AYES: 10 NOES: 0 PRESENT: 0",
      "date": "2026-01-29T06:00:00+00:00",
      "organization_id": "~{\"classification\": \"lower\"}",
      "classification": [
        "committee-passage"
      ],
      "related_entities": [],
      "_processing": {
        "log_file_created": "2026-07-13T06:05:21Z"
      }
    },
    {
      "description": "Placed on the Informal Perfection Calendar (H)",
      "date": "2026-02-03T06:00:00+00:00",
      "organization_id": "~{\"classification\": \"lower\"}",
      "classification": [],
      "related_entities": [],
      "_processing": {
        "log_file_created": "2026-07-13T06:05:21Z"
      }
    },
    {
      "description": "Taken Up for Perfection (H)",
      "date": "2026-02-04T06:00:00+00:00",
      "organization_id": "~{\"classification\": \"lower\"}",
      "classification": [],
      "related_entities": [],
      "_processing": {
        "log_file_created": "2026-07-13T06:05:21Z"
      }
    },
    {
      "description": "Title of Bill - Agreed To",
      "date": "2026-02-04T06:00:00+00:00",
      "organization_id": "~{\"classification\": \"lower\"}",
      "classification": [],
      "related_entities": [],
      "_processing": {
        "log_file_created": "2026-07-13T06:05:21Z"
      }
    },
    {
      "description": "HCS Adopted (H)",
      "date": "2026-02-04T06:00:00+00:00",
      "organization_id": "~{\"classification\": \"lower\"}",
      "classification": [],
      "related_entities": [],
      "_processing": {
        "log_file_created": "2026-07-13T06:05:21Z"
      }
    },
    {
      "description": "Perfected (H)",
      "date": "2026-02-04T06:00:00+00:00",
      "organization_id": "~{\"classification\": \"lower\"}",
      "classification": [],
      "related_entities": [],
      "_processing": {
        "log_file_created": "2026-07-13T06:05:21Z"
      }
    },
    {
      "description": "Taken Up for Third Reading (H)",
      "date": "2026-02-05T06:00:00+00:00",
      "organization_id": "~{\"classification\": \"lower\"}",
      "classification": [
        "reading-3"
      ],
      "related_entities": [],
      "_processing": {
        "log_file_created": "2026-07-13T06:05:21Z"
      }
    },
    {
      "description": "Third Read and Passed (H) - AYES: 149 NOES: 0 PRESENT: 2",
      "date": "2026-02-05T06:00:00+00:00",
      "organization_id": "~{\"classification\": \"lower\"}",
      "classification": [
        "passage",
        "reading-3"
      ],
      "related_entities": [],
      "_processing": {
        "log_file_created": "2026-07-13T06:05:21Z"
      }
    },
    {
      "description": "Reported to the Senate and First Read (S)",
      "date": "2026-02-05T06:00:00+00:00",
      "organization_id": "~{\"classification\": \"upper\"}",
      "classification": [
        "reading-1"
      ],
      "related_entities": [],
      "_processing": {
        "log_file_created": "2026-07-13T06:05:21Z"
      }
    },
    {
      "description": "Second read and referred: General Laws(S)",
      "date": "2026-02-26T06:00:00+00:00",
      "organization_id": "~{\"classification\": \"upper\"}",
      "classification": [],
      "related_entities": [],
      "_processing": {
        "log_file_created": "2026-07-13T06:05:21Z"
      }
    },
    {
      "description": "Public Hearing Scheduled (S) - Wednesday, March 25, 2026, 12:00 p.m., Senate Committee Room-1st Floor",
      "date": "2026-03-25T05:00:00+00:00",
      "organization_id": "~{\"classification\": \"upper\"}",
      "classification": [],
      "related_entities": [],
      "_processing": {
        "log_file_created": "2026-07-13T06:05:21Z"
      }
    }
  ],
  "sponsorships": [
    {
      "name": "Mazzie Christensen",
      "classification": "primary",
      "entity_type": "person",
      "primary": true,
      "person_id": "~{\"name\": \"Mazzie Christensen\"}",
      "organization_id": null
    },
    {
      "name": "George Hruza",
      "classification": "cosponsor",
      "entity_type": "person",
      "primary": false,
      "person_id": "~{\"name\": \"George Hruza\"}",
      "organization_id": null
    },
    {
      "name": "Donna Barnes",
      "classification": "cosponsor",
      "entity_type": "person",
      "primary": false,
      "person_id": "~{\"name\": \"Donna Barnes\"}",
      "organization_id": null
    },
    {
      "name": "Mitch Boggs",
      "classification": "cosponsor",
      "entity_type": "person",
      "primary": false,
      "person_id": "~{\"name\": \"Mitch Boggs\"}",
      "organization_id": null
    },
    {
      "name": "Ron Fowler",
      "classification": "cosponsor",
      "entity_type": "person",
      "primary": false,
      "person_id": "~{\"name\": \"Ron Fowler\"}",
      "organization_id": null
    },
    {
      "name": "Bob Titus",
      "classification": "cosponsor",
      "entity_type": "person",
      "primary": false,
      "person_id": "~{\"name\": \"Bob Titus\"}",
      "organization_id": null
    },
    {
      "name": "David Dolan",
      "classification": "cosponsor",
      "entity_type": "person",
      "primary": false,
      "person_id": "~{\"name\": \"David Dolan\"}",
      "organization_id": null
    },
    {
      "name": "John Hewkin",
      "classification": "cosponsor",
      "entity_type": "person",
      "primary": false,
      "person_id": "~{\"name\": \"John Hewkin\"}",
      "organization_id": null
    },
    {
      "name": "Burt Whaley",
      "classification": "cosponsor",
      "entity_type": "person",
      "primary": false,
      "person_id": "~{\"name\": \"Burt Whaley\"}",
      "organization_id": null
    },
    {
      "name": "Brian Seitz",
      "classification": "cosponsor",
      "entity_type": "person",
      "primary": false,
      "person_id": "~{\"name\": \"Brian Seitz\"}",
      "organization_id": null
    },
    {
      "name": "Deanna Self",
      "classification": "cosponsor",
      "entity_type": "person",
      "primary": false,
      "person_id": "~{\"name\": \"Deanna Self\"}",
      "organization_id": null
    },
    {
      "name": "Danny Busick",
      "classification": "cosponsor",
      "entity_type": "person",
      "primary": false,
      "person_id": "~{\"name\": \"Danny Busick\"}",
      "organization_id": null
    }
  ],
  "related_bills": [],
  "versions": [
    {
      "note": "Introduced",
      "links": [
        {
          "url": "https://documents.house.mo.gov/billtracking/bills261/hlrbillspdf/3951H.02I.pdf",
          "media_type": "application/pdf"
        }
      ],
      "date": "",
      "classification": ""
    },
    {
      "note": "House Committee Substitute",
      "links": [
        {
          "url": "https://documents.house.mo.gov/billtracking/bills261/hlrbillspdf/3951H.05C.pdf",
          "media_type": "application/pdf"
        }
      ],
      "date": "",
      "classification": ""
    },
    {
      "note": "Perfected",
      "links": [
        {
          "url": "https://documents.house.mo.gov/billtracking/bills261/hlrbillspdf/3951H.05P.pdf",
          "media_type": "application/pdf"
        }
      ],
      "date": "",
      "classification": ""
    }
  ],
  "documents": [
    {
      "note": "Bill Summary (Introduced)",
      "links": [
        {
          "url": "https://documents.house.mo.gov/billtracking/bills261/sumpdf/HB1694I.pdf",
          "media_type": "application/pdf"
        }
      ],
      "date": "",
      "classification": ""
    },
    {
      "note": "Bill Summary (House Committee Substitute)",
      "links": [
        {
          "url": "https://documents.house.mo.gov/billtracking/bills261/sumpdf/HB1694C.pdf",
          "media_type": "application/pdf"
        }
      ],
      "date": "",
      "classification": ""
    },
    {
      "note": "Bill Summary (Perfected)",
      "links": [
        {
          "url": "https://documents.house.mo.gov/billtracking/bills261/sumpdf/HB1694P.pdf",
          "media_type": "application/pdf"
        }
      ],
      "date": "",
      "classification": ""
    },
    {
      "note": "Fiscal Note 3951H.02I.ORG",
      "links": [
        {
          "url": "https://documents.house.mo.gov/billtracking/bills261/fiscal/fispdf/3951H.02I.ORG.pdf",
          "media_type": "application/pdf"
        }
      ],
      "date": "",
      "classification": ""
    },
    {
      "note": "Fiscal Note 3951H.05C.ORG",
      "links": [
        {
          "url": "https://documents.house.mo.gov/billtracking/bills261/fiscal/fispdf/3951H.05C.ORG.pdf",
          "media_type": "application/pdf"
        }
      ],
      "date": "",
      "classification": ""
    },
    {
      "note": "Fiscal Note 3951H.05P.ORG",
      "links": [
        {
          "url": "https://documents.house.mo.gov/billtracking/bills261/fiscal/fispdf/3951H.05P.ORG.pdf",
          "media_type": "application/pdf"
        }
      ],
      "date": "",
      "classification": ""
    },
    {
      "note": "Bill Summary (Witnesses)",
      "links": [
        {
          "url": "https://documents.house.mo.gov/billtracking/bills261/witnesses/HB1694Testimony1-14.pdf",
          "media_type": "application/pdf"
        }
      ],
      "date": "",
      "classification": ""
    }
  ],
  "citations": [],
  "sources": [
    {
      "url": "https://www.house.mo.gov/BillContent.aspx?bill=HB1694&year=2026&code=R&style=new",
      "note": ""
    },
    {
      "url": "https://house.mo.gov/billactions.aspx?bill=HB1694&year=2026&code=R",
      "note": ""
    }
  ],
  "extras": {},
  "jurisdiction": {
    "id": "ocd-jurisdiction/country:us/state:mo/government",
    "name": "Missouri",
    "classification": "state",
    "division_id": "ocd-division/country:us/state:mo"
  },
  "_processing": {
    "logs_latest_update": "2026-07-13T06:05:21Z"
  }
}