{
  "legislative_session": "2026",
  "identifier": "SB 1188",
  "title": "SB 1188 - This act modifies provisions relating to tax credits.\r\n\r\nPROGRAM SUNSETS\r\n\tThis act adds a sunset date of August 28, 2032, to the following tax credits and programs:\r\n\r\n1.\tNeighborhood Assistance Act (Section 32.125)\r\n2.\tMDFB loan security and contribution tax credit (Section 100.286)\r\n3.\tJobs Now Act (Section 100.293)\r\n4.\tBusiness Use Incentives for Large-Scale Development (BUILD) (Section 100.850)\r\n5.\tInvestments in Missouri Small Businesses (Section 135.432)\r\n6.\tYouth Opportunities and Violence Prevention (Section 135.460)\r\n7.\tRehabilitation and Construction of Residences in Distressed Communities (Section 135.487)\r\n8.\tSmall Business Expenditures for ADA Access (Section 135.490)\r\n9.\tCommunity-Based Faculty Preceptor (Section 135.690)\r\n10.\tResidential Treatment Agency Tax Credit (Section 135.1150)\r\n11.\tDevelopmental Disability Care Provider (Section 135.1180)\r\n12.\tBank S Corporation Tax Credit (Section 143.471)\r\n13.\tShared Care Tax Credit (Section 192.2015)\r\n14.\tFamily Development Account Contribution Tax Credit (Section 208.770)\r\n15.\tFamily Farms Act Tax Credit (Section 348.505)\r\n16.\tAbandoned Property Tax Credit (Section 447.708)\r\n\r\n\tThis act adds a sunset date of August 28, 2029, to the following tax credits and programs:\r\n\r\n1.\tMissouri Working Family Tax Credit (Section 143.177)\r\n\r\nTAX CREDIT ADMINISTERING AGENCIES\r\n\tThis act transfers the administering agency for the following tax credits:\r\n\r\n1.\tSurviving Spouses of Public Safety Officers, to the Department of Public Safety (Section 135.090)\r\n2.\tAdoption Tax Credit Act, to the Department of Social Services (Sections 135.326 and 135.339)\r\n3.\tChampion for Children, to the Department of Social Services (Section 135.341)\r\n4.\tSmall Business Expenditures for ADA Access, to the Department of Economic Development (Section 135.490)\r\n5.\tResidential Renovations for Disability, to the Department of Economic Development (Section 135.562)\r\n6.\tDonated Food, to the Department of Social Services (Section 135.647)\r\n7.\tHigh Ethanol Blend Retailer Tax Credit, to the Department of Agriculture (Section 135.772)\r\n8.\tBiodiesel Blend Retailer Tax Credit, to the Department of Agriculture (Section 135.775)\r\n9.\tBiodiesel Producer Tax Credit, to the Department of Agriculture (Section 135.778)\r\n\r\nTAX CREDIT ANNUAL LIMITS\r\n\tFor the following tax credits, beginning with FY 2027, the act applies an annual limit on the amount of tax credits that may be issued in a fiscal year. The limit shall be equal to the highest amount of tax credits issued for such tax credit during FY 2024-2026 period:\r\n\r\n1.\tSurviving Spouses of Public Safety Officers, to the Department of Public Safety (Section 135.090)\r\n2.\tNew or Expanded Business Facility (Section 135.110)\r\n3.\tSmall Business Expenditures for ADA Access (Section 135.490)\r\n4.\tResidential Treatment Agency Tax Credit (Section 135.1150)\r\n5.\tDevelopmental Disability Care Provider (Section 135.1180)\r\n6.\tSelf-employed Health Insurance Tax Credit (Section 143.119)\r\n7.\tBank S Corporation Tax Credit (Section 143.471)\r\n8.\tShared Care Tax Credit (Section 192.2015)\r\n9.\tAbandoned Property Tax Credit (Section 447.708)\r\n\r\n\tFor the following tax credits, beginning January 1, 2028, the act applies an annual limit on the amount of tax credits that may be issued in a calendar year. The limit shall be equal to the highest amount of tax credits issued for such tax credit during FY 2025-2027 period:\r\n\r\n1.\tMissouri Working Family Tax Credit (Section 143.177)\r\n\r\nTAX CREDIT APPROPRIATIONS (Section 135.835)\r\n\tFor all tax years beginning on or after January 1, 2027, this act places a maximum three year carry-forward on all tax credit programs. Additionally, the act subjects all tax credits to appropriations, with the following exceptions:\r\n\r\n1.\tLow-Income Housing Tax Credit (Section 135.352)\r\n2.\tShow MO Act (Section 135.750)\r\n3.\tSelf-employed Health Insurance Tax Credit (Section 143.119)\r\n4.\tMissouri Working Family Tax Credit (Section 143.177)\r\n5.\tSALT Parity Tax Credit (Section 143.436)\r\n6.\tBank S Corporation Tax Credit (Section 143.471)\r\n7.\tBank Franchise Tax Credit (Section 148.030)\r\n\r\nREPEAL OF TAX CREDITS\r\n\tThis act repeals the following tax credit programs:\r\n\r\n1.\tDistressed Areas Land Assemblage Tax Credit (Section 99.1205)\r\n2.\tCharcoal Producers Tax Credit (Section 135.313)\r\n3.\tMissouri Certified Capital Company Law (Sections 135.500 to 135.529)\r\n4.\tDistressed Community Tax Credits (Sections 135.535 to 135.546)\r\n5.\tQualified Beef Tax Credit (Section 135.679)\r\n6.\tQualified Equity Investment Tax Credit (Sections 135.680 and 135.682)\r\n7.\tWine and Grape Production Tax Credit (Section 135.700)\r\n8.\tAlternative Fuel Vehicle Refueling Property Tax Credit (Section 135.710)\r\n9.\tSmall Business Guaranty Fee Tax Credit (Section 135.766)\r\n10.\tEnhanced Enterprise Zones (Sections 135.950 to 135.973)\r\n11.\tUnmet Health, Hunger, and Hygiene Needs of Children in School Tax Credit (Section 135.1125)\r\n12.\tHigher Education Scholarship Donation Tax Credit (Section 173.196)\r\n13.\tDry Fire Hydrant Tax Credit (Section 320.093)\r\n14.\tInnovation Center Contribution Tax Credit (Sections 348.300 to 348.318)\r\n15.\tNew Enterprise Creation Act (Sections 620.635 to 620.653)\r\n16.\tMissouri Quality Jobs Act (Sections 620.1875 to 620.1890)\r\n17.\tInnovation Campus Tax Credit (Section 620.2600)\r\nJOSH NORBERG",
  "from_organization": "~{\"classification\": \"upper\"}",
  "classification": [
    "bill"
  ],
  "subject": [],
  "abstracts": [
    {
      "note": "abstract",
      "abstract": "SB 1188 - This act modifies provisions relating to tax credits.\r\n\r\nPROGRAM SUNSETS\r\n\tThis act adds a sunset date of August 28, 2032, to the following tax credits and programs:\r\n\r\n1.\tNeighborhood Assistance Act (Section 32.125)\r\n2.\tMDFB loan security and contribution tax credit (Section 100.286)\r\n3.\tJobs Now Act (Section 100.293)\r\n4.\tBusiness Use Incentives for Large-Scale Development (BUILD) (Section 100.850)\r\n5.\tInvestments in Missouri Small Businesses (Section 135.432)\r\n6.\tYouth Opportunities and Violence Prevention (Section 135.460)\r\n7.\tRehabilitation and Construction of Residences in Distressed Communities (Section 135.487)\r\n8.\tSmall Business Expenditures for ADA Access (Section 135.490)\r\n9.\tCommunity-Based Faculty Preceptor (Section 135.690)\r\n10.\tResidential Treatment Agency Tax Credit (Section 135.1150)\r\n11.\tDevelopmental Disability Care Provider (Section 135.1180)\r\n12.\tBank S Corporation Tax Credit (Section 143.471)\r\n13.\tShared Care Tax Credit (Section 192.2015)\r\n14.\tFamily Development Account Contribution Tax Credit (Section 208.770)\r\n15.\tFamily Farms Act Tax Credit (Section 348.505)\r\n16.\tAbandoned Property Tax Credit (Section 447.708)\r\n\r\n\tThis act adds a sunset date of August 28, 2029, to the following tax credits and programs:\r\n\r\n1.\tMissouri Working Family Tax Credit (Section 143.177)\r\n\r\nTAX CREDIT ADMINISTERING AGENCIES\r\n\tThis act transfers the administering agency for the following tax credits:\r\n\r\n1.\tSurviving Spouses of Public Safety Officers, to the Department of Public Safety (Section 135.090)\r\n2.\tAdoption Tax Credit Act, to the Department of Social Services (Sections 135.326 and 135.339)\r\n3.\tChampion for Children, to the Department of Social Services (Section 135.341)\r\n4.\tSmall Business Expenditures for ADA Access, to the Department of Economic Development (Section 135.490)\r\n5.\tResidential Renovations for Disability, to the Department of Economic Development (Section 135.562)\r\n6.\tDonated Food, to the Department of Social Services (Section 135.647)\r\n7.\tHigh Ethanol Blend Retailer Tax Credit, to the Department of Agriculture (Section 135.772)\r\n8.\tBiodiesel Blend Retailer Tax Credit, to the Department of Agriculture (Section 135.775)\r\n9.\tBiodiesel Producer Tax Credit, to the Department of Agriculture (Section 135.778)\r\n\r\nTAX CREDIT ANNUAL LIMITS\r\n\tFor the following tax credits, beginning with FY 2027, the act applies an annual limit on the amount of tax credits that may be issued in a fiscal year. The limit shall be equal to the highest amount of tax credits issued for such tax credit during FY 2024-2026 period:\r\n\r\n1.\tSurviving Spouses of Public Safety Officers, to the Department of Public Safety (Section 135.090)\r\n2.\tNew or Expanded Business Facility (Section 135.110)\r\n3.\tSmall Business Expenditures for ADA Access (Section 135.490)\r\n4.\tResidential Treatment Agency Tax Credit (Section 135.1150)\r\n5.\tDevelopmental Disability Care Provider (Section 135.1180)\r\n6.\tSelf-employed Health Insurance Tax Credit (Section 143.119)\r\n7.\tBank S Corporation Tax Credit (Section 143.471)\r\n8.\tShared Care Tax Credit (Section 192.2015)\r\n9.\tAbandoned Property Tax Credit (Section 447.708)\r\n\r\n\tFor the following tax credits, beginning January 1, 2028, the act applies an annual limit on the amount of tax credits that may be issued in a calendar year. The limit shall be equal to the highest amount of tax credits issued for such tax credit during FY 2025-2027 period:\r\n\r\n1.\tMissouri Working Family Tax Credit (Section 143.177)\r\n\r\nTAX CREDIT APPROPRIATIONS (Section 135.835)\r\n\tFor all tax years beginning on or after January 1, 2027, this act places a maximum three year carry-forward on all tax credit programs. Additionally, the act subjects all tax credits to appropriations, with the following exceptions:\r\n\r\n1.\tLow-Income Housing Tax Credit (Section 135.352)\r\n2.\tShow MO Act (Section 135.750)\r\n3.\tSelf-employed Health Insurance Tax Credit (Section 143.119)\r\n4.\tMissouri Working Family Tax Credit (Section 143.177)\r\n5.\tSALT Parity Tax Credit (Section 143.436)\r\n6.\tBank S Corporation Tax Credit (Section 143.471)\r\n7.\tBank Franchise Tax Credit (Section 148.030)\r\n\r\nREPEAL OF TAX CREDITS\r\n\tThis act repeals the following tax credit programs:\r\n\r\n1.\tDistressed Areas Land Assemblage Tax Credit (Section 99.1205)\r\n2.\tCharcoal Producers Tax Credit (Section 135.313)\r\n3.\tMissouri Certified Capital Company Law (Sections 135.500 to 135.529)\r\n4.\tDistressed Community Tax Credits (Sections 135.535 to 135.546)\r\n5.\tQualified Beef Tax Credit (Section 135.679)\r\n6.\tQualified Equity Investment Tax Credit (Sections 135.680 and 135.682)\r\n7.\tWine and Grape Production Tax Credit (Section 135.700)\r\n8.\tAlternative Fuel Vehicle Refueling Property Tax Credit (Section 135.710)\r\n9.\tSmall Business Guaranty Fee Tax Credit (Section 135.766)\r\n10.\tEnhanced Enterprise Zones (Sections 135.950 to 135.973)\r\n11.\tUnmet Health, Hunger, and Hygiene Needs of Children in School Tax Credit (Section 135.1125)\r\n12.\tHigher Education Scholarship Donation Tax Credit (Section 173.196)\r\n13.\tDry Fire Hydrant Tax Credit (Section 320.093)\r\n14.\tInnovation Center Contribution Tax Credit (Sections 348.300 to 348.318)\r\n15.\tNew Enterprise Creation Act (Sections 620.635 to 620.653)\r\n16.\tMissouri Quality Jobs Act (Sections 620.1875 to 620.1890)\r\n17.\tInnovation Campus Tax Credit (Section 620.2600)\r\nJOSH NORBERG"
    }
  ],
  "other_titles": [
    {
      "note": "",
      "title": "Modifies provisions relating to tax credits"
    }
  ],
  "other_identifiers": [
    {
      "identifier": "ocd-bill-mo-2026-sb1188"
    }
  ],
  "actions": [
    {
      "description": "Second Read and Referred S Economic and Workforce Development Committee",
      "date": "2026-01-27T06:00:00+00:00",
      "organization_id": "~{\"classification\": \"upper\"}",
      "classification": [
        "reading-2",
        "referral-committee"
      ],
      "related_entities": [],
      "_processing": {
        "log_file_created": "2026-07-13T06:05:20Z"
      }
    },
    {
      "description": "S First Read",
      "date": "2026-01-07T06:00:00+00:00",
      "organization_id": "~{\"classification\": \"upper\"}",
      "classification": [
        "reading-1"
      ],
      "related_entities": [],
      "_processing": {
        "log_file_created": "2026-07-13T06:05:20Z"
      }
    },
    {
      "description": "Prefiled",
      "date": "2025-12-01T06:00:00+00:00",
      "organization_id": "~{\"classification\": \"upper\"}",
      "classification": [],
      "related_entities": [],
      "_processing": {
        "log_file_created": "2026-07-13T06:05:20Z"
      }
    }
  ],
  "sponsorships": [
    {
      "name": "Coleman, Mary Elizabeth",
      "classification": "primary",
      "entity_type": "person",
      "primary": true,
      "person_id": "~{\"chamber\": \"upper\", \"name\": \"\\r\\n                                            Coleman, Mary Elizabeth\\r\\n                                \"}",
      "organization_id": null
    }
  ],
  "related_bills": [],
  "versions": [
    {
      "note": "4418S.02I - Introduced",
      "links": [
        {
          "url": "https://www.senate.mo.gov/26info/pdf-bill/intro/SB1188.pdf",
          "media_type": "application/pdf"
        }
      ],
      "date": "",
      "classification": ""
    }
  ],
  "documents": [],
  "citations": [],
  "sources": [
    {
      "url": "https://www.senate.mo.gov/BillTracking/Bills/BillInformation?year=2026&billid=605",
      "note": ""
    }
  ],
  "extras": {
    "MO_BILL_LR": "4418S.02I"
  },
  "jurisdiction": {
    "id": "ocd-jurisdiction/country:us/state:mo/government",
    "name": "Missouri",
    "classification": "state",
    "division_id": "ocd-division/country:us/state:mo"
  },
  "_processing": {
    "logs_latest_update": "2026-07-13T06:05:20Z",
    "text_extraction_latest_update": "2026-07-21T07:42:23.881947Z"
  }
}