{
  "legislative_session": "2026",
  "identifier": "HB 2292",
  "title": "Modifies provisions relating to abuse and neglect reporting, including a requirement to report companion animal abuse",
  "from_organization": "~{\"classification\": \"lower\"}",
  "classification": [
    "bill"
  ],
  "subject": [],
  "abstracts": [],
  "other_titles": [
    {
      "note": "official",
      "title": "SS#2 SCS HCS HB 2292"
    }
  ],
  "other_identifiers": [
    {
      "identifier": "ocd-bill-mo-2026-hb2292"
    }
  ],
  "actions": [
    {
      "description": "Prefiled (H)",
      "date": "2025-12-09T06:00:00+00:00",
      "organization_id": "~{\"classification\": \"lower\"}",
      "classification": [],
      "related_entities": [],
      "_processing": {
        "log_file_created": "2026-07-13T06:05:22Z"
      }
    },
    {
      "description": "Read First Time (H)",
      "date": "2026-01-07T06:00:00+00:00",
      "organization_id": "~{\"classification\": \"lower\"}",
      "classification": [],
      "related_entities": [],
      "_processing": {
        "log_file_created": "2026-07-13T06:05:22Z"
      }
    },
    {
      "description": "Read Second Time (H)",
      "date": "2026-01-08T06:00:00+00:00",
      "organization_id": "~{\"classification\": \"lower\"}",
      "classification": [
        "reading-2"
      ],
      "related_entities": [],
      "_processing": {
        "log_file_created": "2026-07-13T06:05:22Z"
      }
    },
    {
      "description": "Referred: Special Committee on Urban Issues(H)",
      "date": "2026-01-22T06:00:00+00:00",
      "organization_id": "~{\"classification\": \"lower\"}",
      "classification": [
        "referral-committee"
      ],
      "related_entities": [],
      "_processing": {
        "log_file_created": "2026-07-13T06:05:22Z"
      }
    },
    {
      "description": "Public Hearing Completed (H)",
      "date": "2026-02-11T06:00:00+00:00",
      "organization_id": "~{\"classification\": \"lower\"}",
      "classification": [],
      "related_entities": [],
      "_processing": {
        "log_file_created": "2026-07-13T06:05:22Z"
      }
    },
    {
      "description": "Executive Session Completed (H)",
      "date": "2026-02-19T06:00:00+00:00",
      "organization_id": "~{\"classification\": \"lower\"}",
      "classification": [],
      "related_entities": [],
      "_processing": {
        "log_file_created": "2026-07-13T06:05:22Z"
      }
    },
    {
      "description": "HCS Voted Do Pass (H)",
      "date": "2026-02-19T06:00:00+00:00",
      "organization_id": "~{\"classification\": \"lower\"}",
      "classification": [
        "committee-passage"
      ],
      "related_entities": [],
      "_processing": {
        "log_file_created": "2026-07-13T06:05:22Z"
      }
    },
    {
      "description": "HCS Reported Do Pass (H) - AYES: 6 NOES: 0 PRESENT: 0",
      "date": "2026-02-23T06:00:00+00:00",
      "organization_id": "~{\"classification\": \"lower\"}",
      "classification": [
        "committee-passage"
      ],
      "related_entities": [],
      "_processing": {
        "log_file_created": "2026-07-13T06:05:22Z"
      }
    },
    {
      "description": "Referred: Rules - Legislative(H)",
      "date": "2026-02-24T06:00:00+00:00",
      "organization_id": "~{\"classification\": \"lower\"}",
      "classification": [
        "referral-committee"
      ],
      "related_entities": [],
      "_processing": {
        "log_file_created": "2026-07-13T06:05:22Z"
      }
    },
    {
      "description": "Executive Session Completed (H)",
      "date": "2026-03-05T06:00:00+00:00",
      "organization_id": "~{\"classification\": \"lower\"}",
      "classification": [],
      "related_entities": [],
      "_processing": {
        "log_file_created": "2026-07-13T06:05:22Z"
      }
    },
    {
      "description": "Voted Do Pass (H)",
      "date": "2026-03-05T06:00:00+00:00",
      "organization_id": "~{\"classification\": \"lower\"}",
      "classification": [
        "committee-passage"
      ],
      "related_entities": [],
      "_processing": {
        "log_file_created": "2026-07-13T06:05:22Z"
      }
    },
    {
      "description": "Reported Do Pass (H) - AYES: 12 NOES: 0 PRESENT: 0",
      "date": "2026-03-05T06:00:00+00:00",
      "organization_id": "~{\"classification\": \"lower\"}",
      "classification": [
        "committee-passage"
      ],
      "related_entities": [],
      "_processing": {
        "log_file_created": "2026-07-13T06:05:22Z"
      }
    },
    {
      "description": "Placed on the Informal Perfection Calendar (H)",
      "date": "2026-03-23T05:00:00+00:00",
      "organization_id": "~{\"classification\": \"lower\"}",
      "classification": [],
      "related_entities": [],
      "_processing": {
        "log_file_created": "2026-07-13T06:05:22Z"
      }
    },
    {
      "description": "Taken Up for Perfection (H)",
      "date": "2026-04-01T05:00:00+00:00",
      "organization_id": "~{\"classification\": \"lower\"}",
      "classification": [],
      "related_entities": [],
      "_processing": {
        "log_file_created": "2026-07-13T06:05:22Z"
      }
    },
    {
      "description": "Title of Bill - Agreed To",
      "date": "2026-04-01T05:00:00+00:00",
      "organization_id": "~{\"classification\": \"lower\"}",
      "classification": [],
      "related_entities": [],
      "_processing": {
        "log_file_created": "2026-07-13T06:05:22Z"
      }
    },
    {
      "description": "HCS Adopted (H)",
      "date": "2026-04-01T05:00:00+00:00",
      "organization_id": "~{\"classification\": \"lower\"}",
      "classification": [],
      "related_entities": [],
      "_processing": {
        "log_file_created": "2026-07-13T06:05:22Z"
      }
    },
    {
      "description": "Perfected with Amendments (H) - HA 1, HA 2, adopted",
      "date": "2026-04-01T05:00:00+00:00",
      "organization_id": "~{\"classification\": \"lower\"}",
      "classification": [],
      "related_entities": [],
      "_processing": {
        "log_file_created": "2026-07-13T06:05:22Z"
      }
    },
    {
      "description": "Referred: Fiscal Review(H)",
      "date": "2026-04-02T05:00:00+00:00",
      "organization_id": "~{\"classification\": \"lower\"}",
      "classification": [
        "referral-committee"
      ],
      "related_entities": [],
      "_processing": {
        "log_file_created": "2026-07-13T06:05:22Z"
      }
    },
    {
      "description": "Placed on the Informal Third Reading Calendar (H)",
      "date": "2026-04-07T05:00:00+00:00",
      "organization_id": "~{\"classification\": \"lower\"}",
      "classification": [
        "reading-3"
      ],
      "related_entities": [],
      "_processing": {
        "log_file_created": "2026-07-13T06:05:22Z"
      }
    },
    {
      "description": "Executive Session Completed (H)",
      "date": "2026-04-08T05:00:00+00:00",
      "organization_id": "~{\"classification\": \"lower\"}",
      "classification": [],
      "related_entities": [],
      "_processing": {
        "log_file_created": "2026-07-13T06:05:22Z"
      }
    },
    {
      "description": "Voted Do Pass (H)",
      "date": "2026-04-08T05:00:00+00:00",
      "organization_id": "~{\"classification\": \"lower\"}",
      "classification": [
        "committee-passage"
      ],
      "related_entities": [],
      "_processing": {
        "log_file_created": "2026-07-13T06:05:22Z"
      }
    },
    {
      "description": "Reported Do Pass (H) - AYES: 7 NOES: 0 PRESENT: 0",
      "date": "2026-04-08T05:00:00+00:00",
      "organization_id": "~{\"classification\": \"lower\"}",
      "classification": [
        "committee-passage"
      ],
      "related_entities": [],
      "_processing": {
        "log_file_created": "2026-07-13T06:05:22Z"
      }
    },
    {
      "description": "Taken Up for Third Reading (H)",
      "date": "2026-04-09T05:00:00+00:00",
      "organization_id": "~{\"classification\": \"lower\"}",
      "classification": [
        "reading-3"
      ],
      "related_entities": [],
      "_processing": {
        "log_file_created": "2026-07-13T06:05:22Z"
      }
    },
    {
      "description": "Third Read and Passed (H) - AYES: 125 NOES: 12 PRESENT: 0",
      "date": "2026-04-09T05:00:00+00:00",
      "organization_id": "~{\"classification\": \"lower\"}",
      "classification": [
        "passage",
        "reading-3"
      ],
      "related_entities": [],
      "_processing": {
        "log_file_created": "2026-07-13T06:05:22Z"
      }
    },
    {
      "description": "Reported to the Senate and First Read (S)",
      "date": "2026-04-13T05:00:00+00:00",
      "organization_id": "~{\"classification\": \"upper\"}",
      "classification": [
        "reading-1"
      ],
      "related_entities": [],
      "_processing": {
        "log_file_created": "2026-07-13T06:05:22Z"
      }
    },
    {
      "description": "Second read and referred: Agriculture, Food Production and Outdoor Resources(S)",
      "date": "2026-04-21T05:00:00+00:00",
      "organization_id": "~{\"classification\": \"upper\"}",
      "classification": [],
      "related_entities": [],
      "_processing": {
        "log_file_created": "2026-07-13T06:05:22Z"
      }
    },
    {
      "description": "Public Hearing Scheduled (S) - Thursday, April 30, 2026, 8:30 a.m., Senate Committee Room 1 - 1st Floor",
      "date": "2026-04-28T05:00:00+00:00",
      "organization_id": "~{\"classification\": \"upper\"}",
      "classification": [],
      "related_entities": [],
      "_processing": {
        "log_file_created": "2026-07-13T06:05:22Z"
      }
    },
    {
      "description": "Public Hearing Scheduled, Bill not Heard (S)",
      "date": "2026-04-30T05:00:00+00:00",
      "organization_id": "~{\"classification\": \"upper\"}",
      "classification": [],
      "related_entities": [],
      "_processing": {
        "log_file_created": "2026-07-13T06:05:22Z"
      }
    },
    {
      "description": "Re-referred to Committee: Rules, Joint Rules, Resolutions and Ethics(S)",
      "date": "2026-04-30T05:00:00+00:00",
      "organization_id": "~{\"classification\": \"upper\"}",
      "classification": [],
      "related_entities": [],
      "_processing": {
        "log_file_created": "2026-07-13T06:05:22Z"
      }
    },
    {
      "description": "Public Hearing Scheduled (S) - Monday, May 4, 2026, 3:30 p.m., Senate Lounge - 3rd FLoor",
      "date": "2026-04-30T05:00:00+00:00",
      "organization_id": "~{\"classification\": \"upper\"}",
      "classification": [],
      "related_entities": [],
      "_processing": {
        "log_file_created": "2026-07-13T06:05:22Z"
      }
    },
    {
      "description": "Public Hearing Held (S)",
      "date": "2026-05-04T05:00:00+00:00",
      "organization_id": "~{\"classification\": \"upper\"}",
      "classification": [],
      "related_entities": [],
      "_processing": {
        "log_file_created": "2026-07-13T06:05:22Z"
      }
    },
    {
      "description": "Executive Session Held (S)",
      "date": "2026-05-04T05:00:00+00:00",
      "organization_id": "~{\"classification\": \"upper\"}",
      "classification": [],
      "related_entities": [],
      "_processing": {
        "log_file_created": "2026-07-13T06:05:22Z"
      }
    },
    {
      "description": "SCS Voted Do Pass (S)",
      "date": "2026-05-04T05:00:00+00:00",
      "organization_id": "~{\"classification\": \"upper\"}",
      "classification": [
        "committee-passage"
      ],
      "related_entities": [],
      "_processing": {
        "log_file_created": "2026-07-13T06:05:22Z"
      }
    },
    {
      "description": "SCS Reported Do Pass (S)",
      "date": "2026-05-04T05:00:00+00:00",
      "organization_id": "~{\"classification\": \"upper\"}",
      "classification": [
        "committee-passage"
      ],
      "related_entities": [],
      "_processing": {
        "log_file_created": "2026-07-13T06:05:22Z"
      }
    },
    {
      "description": "Referred: Fiscal Oversight(S)",
      "date": "2026-05-04T05:00:00+00:00",
      "organization_id": "~{\"classification\": \"upper\"}",
      "classification": [
        "referral-committee"
      ],
      "related_entities": [],
      "_processing": {
        "log_file_created": "2026-07-13T06:05:22Z"
      }
    },
    {
      "description": "Executive Session Held (S)",
      "date": "2026-05-07T05:00:00+00:00",
      "organization_id": "~{\"classification\": \"upper\"}",
      "classification": [],
      "related_entities": [],
      "_processing": {
        "log_file_created": "2026-07-13T06:05:22Z"
      }
    },
    {
      "description": "Voted Do Pass (S)",
      "date": "2026-05-07T05:00:00+00:00",
      "organization_id": "~{\"classification\": \"upper\"}",
      "classification": [
        "committee-passage"
      ],
      "related_entities": [],
      "_processing": {
        "log_file_created": "2026-07-13T06:05:22Z"
      }
    },
    {
      "description": "Reported Do Pass (S)",
      "date": "2026-05-07T05:00:00+00:00",
      "organization_id": "~{\"classification\": \"upper\"}",
      "classification": [
        "committee-passage"
      ],
      "related_entities": [],
      "_processing": {
        "log_file_created": "2026-07-13T06:05:22Z"
      }
    },
    {
      "description": "Placed on Informal Calendar",
      "date": "2026-05-07T05:00:00+00:00",
      "organization_id": "~{\"classification\": \"lower\"}",
      "classification": [],
      "related_entities": [],
      "_processing": {
        "log_file_created": "2026-07-13T06:05:22Z"
      }
    },
    {
      "description": "Taken Up for Third Reading (S)",
      "date": "2026-05-14T05:00:00+00:00",
      "organization_id": "~{\"classification\": \"upper\"}",
      "classification": [
        "reading-3"
      ],
      "related_entities": [],
      "_processing": {
        "log_file_created": "2026-07-13T06:05:22Z"
      }
    },
    {
      "description": "SS Offered",
      "date": "2026-05-14T05:00:00+00:00",
      "organization_id": "~{\"classification\": \"lower\"}",
      "classification": [
        "introduction"
      ],
      "related_entities": [],
      "_processing": {
        "log_file_created": "2026-07-13T06:05:22Z"
      }
    },
    {
      "description": "Motion to Table Defeated (H) - SS SCS",
      "date": "2026-05-14T05:00:00+00:00",
      "organization_id": "~{\"classification\": \"lower\"}",
      "classification": [],
      "related_entities": [],
      "_processing": {
        "log_file_created": "2026-07-13T06:05:22Z"
      }
    },
    {
      "description": "Motion to Table Adopted (S) - SA 2",
      "date": "2026-05-14T05:00:00+00:00",
      "organization_id": "~{\"classification\": \"upper\"}",
      "classification": [],
      "related_entities": [],
      "_processing": {
        "log_file_created": "2026-07-13T06:05:22Z"
      }
    },
    {
      "description": "Placed on Informal Calendar",
      "date": "2026-05-14T05:00:00+00:00",
      "organization_id": "~{\"classification\": \"lower\"}",
      "classification": [],
      "related_entities": [],
      "_processing": {
        "log_file_created": "2026-07-13T06:05:22Z"
      }
    },
    {
      "description": "Taken Up",
      "date": "2026-05-15T05:00:00+00:00",
      "organization_id": "~{\"classification\": \"lower\"}",
      "classification": [],
      "related_entities": [],
      "_processing": {
        "log_file_created": "2026-07-13T06:05:22Z"
      }
    },
    {
      "description": "SS Withdrawn (S)",
      "date": "2026-05-15T05:00:00+00:00",
      "organization_id": "~{\"classification\": \"upper\"}",
      "classification": [
        "withdrawal"
      ],
      "related_entities": [],
      "_processing": {
        "log_file_created": "2026-07-13T06:05:22Z"
      }
    },
    {
      "description": "SS#2 Offered (S)",
      "date": "2026-05-15T05:00:00+00:00",
      "organization_id": "~{\"classification\": \"upper\"}",
      "classification": [
        "introduction"
      ],
      "related_entities": [],
      "_processing": {
        "log_file_created": "2026-07-13T06:05:22Z"
      }
    },
    {
      "description": "SS#2 Adopted (S)",
      "date": "2026-05-15T05:00:00+00:00",
      "organization_id": "~{\"classification\": \"upper\"}",
      "classification": [],
      "related_entities": [],
      "_processing": {
        "log_file_created": "2026-07-13T06:05:22Z"
      }
    },
    {
      "description": "Third Read and Passed with Amendments (S) - SA 1 - AYES: 22 NOES: 6 PRESENT: 0",
      "date": "2026-05-15T05:00:00+00:00",
      "organization_id": "~{\"classification\": \"upper\"}",
      "classification": [
        "passage",
        "reading-3"
      ],
      "related_entities": [],
      "_processing": {
        "log_file_created": "2026-07-13T06:05:22Z"
      }
    },
    {
      "description": "Reported to the House with... (H) - SS#2 SCS, as amended",
      "date": "2026-05-15T05:00:00+00:00",
      "organization_id": "~{\"classification\": \"lower\"}",
      "classification": [],
      "related_entities": [],
      "_processing": {
        "log_file_created": "2026-07-13T06:05:22Z"
      }
    },
    {
      "description": "Referred: Fiscal Review(H)",
      "date": "2026-05-15T05:00:00+00:00",
      "organization_id": "~{\"classification\": \"lower\"}",
      "classification": [
        "referral-committee"
      ],
      "related_entities": [],
      "_processing": {
        "log_file_created": "2026-07-13T06:05:22Z"
      }
    },
    {
      "description": "Executive Session Completed (H)",
      "date": "2026-05-15T05:00:00+00:00",
      "organization_id": "~{\"classification\": \"lower\"}",
      "classification": [],
      "related_entities": [],
      "_processing": {
        "log_file_created": "2026-07-13T06:05:22Z"
      }
    },
    {
      "description": "Voted Do Pass (H)",
      "date": "2026-05-15T05:00:00+00:00",
      "organization_id": "~{\"classification\": \"lower\"}",
      "classification": [
        "committee-passage"
      ],
      "related_entities": [],
      "_processing": {
        "log_file_created": "2026-07-13T06:05:22Z"
      }
    },
    {
      "description": "Reported Do Pass (H) - AYES: 8 NOES: 0 PRESENT: 0",
      "date": "2026-05-15T05:00:00+00:00",
      "organization_id": "~{\"classification\": \"lower\"}",
      "classification": [
        "committee-passage"
      ],
      "related_entities": [],
      "_processing": {
        "log_file_created": "2026-07-13T06:05:22Z"
      }
    },
    {
      "description": "Taken Up",
      "date": "2026-05-15T05:00:00+00:00",
      "organization_id": "~{\"classification\": \"lower\"}",
      "classification": [],
      "related_entities": [],
      "_processing": {
        "log_file_created": "2026-07-13T06:05:22Z"
      }
    },
    {
      "description": "House Adopts (H) - SS#2 SCS, as amended",
      "date": "2026-05-15T05:00:00+00:00",
      "organization_id": "~{\"classification\": \"lower\"}",
      "classification": [],
      "related_entities": [],
      "_processing": {
        "log_file_created": "2026-07-13T06:05:22Z"
      }
    },
    {
      "description": "Truly Agreed To and Finally Passed - AYES: 128 NOES: 9 PRESENT: 4",
      "date": "2026-05-15T05:00:00+00:00",
      "organization_id": "~{\"classification\": \"lower\"}",
      "classification": [
        "passage"
      ],
      "related_entities": [],
      "_processing": {
        "log_file_created": "2026-07-13T06:05:22Z"
      }
    },
    {
      "description": "House Message (H)",
      "date": "2026-05-21T05:00:00+00:00",
      "organization_id": "~{\"classification\": \"lower\"}",
      "classification": [],
      "related_entities": [],
      "_processing": {
        "log_file_created": "2026-07-13T06:05:22Z"
      }
    },
    {
      "description": "Signed by House Speaker (H)",
      "date": "2026-05-28T05:00:00+00:00",
      "organization_id": "~{\"classification\": \"lower\"}",
      "classification": [],
      "related_entities": [],
      "_processing": {
        "log_file_created": "2026-07-13T06:05:22Z"
      }
    },
    {
      "description": "Signed by President Pro Tem (S)",
      "date": "2026-05-28T05:00:00+00:00",
      "organization_id": "~{\"classification\": \"upper\"}",
      "classification": [],
      "related_entities": [],
      "_processing": {
        "log_file_created": "2026-07-13T06:05:22Z"
      }
    },
    {
      "description": "Delivered to Governor",
      "date": "2026-05-28T05:00:00+00:00",
      "organization_id": "~{\"classification\": \"executive\"}",
      "classification": [],
      "related_entities": [],
      "_processing": {
        "log_file_created": "2026-07-13T06:05:22Z"
      }
    },
    {
      "description": "Approved by Governor (G)",
      "date": "2026-07-13T05:00:00+00:00",
      "organization_id": "~{\"classification\": \"lower\"}",
      "classification": [
        "executive-signature"
      ],
      "related_entities": [],
      "_processing": {
        "log_file_created": "2026-07-21T03:37:57Z"
      }
    },
    {
      "description": "Delivered to Secretary of State (G)",
      "date": "2026-07-13T05:00:00+00:00",
      "organization_id": "~{\"classification\": \"lower\"}",
      "classification": [],
      "related_entities": [],
      "_processing": {
        "log_file_created": "2026-07-21T03:37:57Z"
      }
    }
  ],
  "sponsorships": [
    {
      "name": "Holly Jones",
      "classification": "primary",
      "entity_type": "person",
      "primary": true,
      "person_id": "~{\"name\": \"Holly Jones\"}",
      "organization_id": null
    },
    {
      "name": "George Hruza",
      "classification": "cosponsor",
      "entity_type": "person",
      "primary": false,
      "person_id": "~{\"name\": \"George Hruza\"}",
      "organization_id": null
    },
    {
      "name": "Mark Sharp",
      "classification": "cosponsor",
      "entity_type": "person",
      "primary": false,
      "person_id": "~{\"name\": \"Mark Sharp\"}",
      "organization_id": null
    },
    {
      "name": "Pattie Mansur",
      "classification": "cosponsor",
      "entity_type": "person",
      "primary": false,
      "person_id": "~{\"name\": \"Pattie Mansur\"}",
      "organization_id": null
    },
    {
      "name": "Kimberly-Ann Collins",
      "classification": "cosponsor",
      "entity_type": "person",
      "primary": false,
      "person_id": "~{\"name\": \"Kimberly-Ann Collins\"}",
      "organization_id": null
    },
    {
      "name": "Doug Clemens",
      "classification": "cosponsor",
      "entity_type": "person",
      "primary": false,
      "person_id": "~{\"name\": \"Doug Clemens\"}",
      "organization_id": null
    },
    {
      "name": "Michael Burton",
      "classification": "cosponsor",
      "entity_type": "person",
      "primary": false,
      "person_id": "~{\"name\": \"Michael Burton\"}",
      "organization_id": null
    },
    {
      "name": "Marla Smith",
      "classification": "cosponsor",
      "entity_type": "person",
      "primary": false,
      "person_id": "~{\"name\": \"Marla Smith\"}",
      "organization_id": null
    }
  ],
  "related_bills": [],
  "versions": [
    {
      "note": "Introduced",
      "links": [
        {
          "url": "https://documents.house.mo.gov/billtracking/bills261/hlrbillspdf/4920H.02I.pdf",
          "media_type": "application/pdf"
        }
      ],
      "date": "",
      "classification": ""
    },
    {
      "note": "House Committee Substitute",
      "links": [
        {
          "url": "https://documents.house.mo.gov/billtracking/bills261/hlrbillspdf/4920H.03C.pdf",
          "media_type": "application/pdf"
        }
      ],
      "date": "",
      "classification": ""
    },
    {
      "note": "Perfected",
      "links": [
        {
          "url": "https://documents.house.mo.gov/billtracking/bills261/hlrbillspdf/4920H.03P.pdf",
          "media_type": "application/pdf"
        }
      ],
      "date": "",
      "classification": ""
    },
    {
      "note": "Senate Committee Substitute",
      "links": [
        {
          "url": "https://documents.house.mo.gov/billtracking/bills261/hlrbillspdf/4920S.05C.pdf",
          "media_type": "application/pdf"
        }
      ],
      "date": "",
      "classification": ""
    },
    {
      "note": "Senate Substitute (Senate Floor Substitute)",
      "links": [
        {
          "url": "https://documents.house.mo.gov/billtracking/bills261/hlrbillspdf/4920S.06F.pdf",
          "media_type": "application/pdf"
        },
        {
          "url": "https://documents.house.mo.gov/billtracking/bills261/hlrbillspdf/4920S.10F.pdf",
          "media_type": "application/pdf"
        }
      ],
      "date": "",
      "classification": ""
    },
    {
      "note": "Truly Agreed and Finally Passed",
      "links": [
        {
          "url": "https://documents.house.mo.gov/billtracking/bills261/hlrbillspdf/4920S.10T.pdf",
          "media_type": "application/pdf"
        }
      ],
      "date": "",
      "classification": ""
    },
    {
      "note": "Amendment HA 2 (Adopted)",
      "links": [
        {
          "url": "https://documents.house.mo.gov/billtracking/bills261/amendpdf/4920H03.01H.pdf",
          "media_type": "application/pdf"
        }
      ],
      "date": "",
      "classification": ""
    },
    {
      "note": "Amendment HA 1 (Adopted)",
      "links": [
        {
          "url": "https://documents.house.mo.gov/billtracking/bills261/amendpdf/4920H03.04H.pdf",
          "media_type": "application/pdf"
        }
      ],
      "date": "",
      "classification": ""
    },
    {
      "note": "Amendment SENATE AMENDMENTS (Distributed)",
      "links": [
        {
          "url": "https://documents.house.mo.gov/billtracking/bills261/amendpdf/4920S10.01F.pdf",
          "media_type": "application/pdf"
        }
      ],
      "date": "",
      "classification": ""
    }
  ],
  "documents": [
    {
      "note": "Bill Summary (Introduced)",
      "links": [
        {
          "url": "https://documents.house.mo.gov/billtracking/bills261/sumpdf/HB2292I.pdf",
          "media_type": "application/pdf"
        }
      ],
      "date": "",
      "classification": ""
    },
    {
      "note": "Bill Summary (House Committee Substitute)",
      "links": [
        {
          "url": "https://documents.house.mo.gov/billtracking/bills261/sumpdf/HB2292C.pdf",
          "media_type": "application/pdf"
        }
      ],
      "date": "",
      "classification": ""
    },
    {
      "note": "Bill Summary (Perfected)",
      "links": [
        {
          "url": "https://documents.house.mo.gov/billtracking/bills261/sumpdf/HB2292P.pdf",
          "media_type": "application/pdf"
        }
      ],
      "date": "",
      "classification": ""
    },
    {
      "note": "Bill Summary (Truly Agreed and Finally Passed)",
      "links": [
        {
          "url": "https://documents.house.mo.gov/billtracking/bills261/sumpdf/HB2292T.pdf",
          "media_type": "application/pdf"
        }
      ],
      "date": "",
      "classification": ""
    },
    {
      "note": "Fiscal Note 4920H.02I.ORG",
      "links": [
        {
          "url": "https://documents.house.mo.gov/billtracking/bills261/fiscal/fispdf/4920H.02I.ORG.pdf",
          "media_type": "application/pdf"
        }
      ],
      "date": "",
      "classification": ""
    },
    {
      "note": "Fiscal Note 4920H.03C.ORG",
      "links": [
        {
          "url": "https://documents.house.mo.gov/billtracking/bills261/fiscal/fispdf/4920H.03C.ORG.pdf",
          "media_type": "application/pdf"
        }
      ],
      "date": "",
      "classification": ""
    },
    {
      "note": "Fiscal Note 4920H.03P.ORG",
      "links": [
        {
          "url": "https://documents.house.mo.gov/billtracking/bills261/fiscal/fispdf/4920H.03P.ORG.pdf",
          "media_type": "application/pdf"
        }
      ],
      "date": "",
      "classification": ""
    },
    {
      "note": "Fiscal Note 4920S.05C.ORG",
      "links": [
        {
          "url": "https://documents.house.mo.gov/billtracking/bills261/fiscal/fispdf/4920S.05C.ORG.pdf",
          "media_type": "application/pdf"
        }
      ],
      "date": "",
      "classification": ""
    },
    {
      "note": "Fiscal Note 4920S.10A.ORG",
      "links": [
        {
          "url": "https://documents.house.mo.gov/billtracking/bills261/fiscal/fispdf/4920S.10A.ORG.pdf",
          "media_type": "application/pdf"
        }
      ],
      "date": "",
      "classification": ""
    },
    {
      "note": "Fiscal Note 4920S.10T.ORG",
      "links": [
        {
          "url": "https://documents.house.mo.gov/billtracking/bills261/fiscal/fispdf/4920S.10T.ORG.pdf",
          "media_type": "application/pdf"
        }
      ],
      "date": "",
      "classification": ""
    },
    {
      "note": "Bill Summary (Witnesses)",
      "links": [
        {
          "url": "https://documents.house.mo.gov/billtracking/bills261/witnesses/HB2292Testimony2-11.pdf",
          "media_type": "application/pdf"
        }
      ],
      "date": "",
      "classification": ""
    }
  ],
  "citations": [],
  "sources": [
    {
      "url": "https://www.house.mo.gov/BillContent.aspx?bill=HB2292&year=2026&code=R&style=new",
      "note": ""
    },
    {
      "url": "https://house.mo.gov/billactions.aspx?bill=HB2292&year=2026&code=R",
      "note": ""
    }
  ],
  "extras": {},
  "jurisdiction": {
    "id": "ocd-jurisdiction/country:us/state:mo/government",
    "name": "Missouri",
    "classification": "state",
    "division_id": "ocd-division/country:us/state:mo"
  },
  "_processing": {
    "logs_latest_update": "2026-07-21T03:37:57Z",
    "text_extraction_latest_update": "2026-07-13T10:35:37.923562Z"
  }
}